Workbook

Sheet Dashboard
D2: Weekly KPI Dashboard
D3: The six numbers every group practice owner needs
D4: from Hello Studio · hellostudio.online
B8: ="Week of "&TEXT('Weekly Entry'!A19,"mmmm d, yyyy") -> Week of April 17, 2026
B11: NEW INQUIRIES | E11: INQUIRY → INTAKE | H11: % OF BOOKED-HOURS GOAL
B12: ='Weekly Entry'!B19 -> 13 | E12: ='Weekly Entry'!D19 -> 0.76923077 | H12: ='Weekly Entry'!G19 -> 0.98
B13: =IF(ISNUMBER('Weekly Entry'!B18),IF('Weekly Entry'!B19-'Weekly Entry'!B18>=0,"▲ ","▼ ")&TEXT(ABS('Weekly Entry'!B19-'Weekly Entry'!B18),"0")&" vs. last week","") -> ▼ 1 vs. last week | E13: =IF(ISNUMBER('Weekly Entry'!D18),IF('Weekly Entry'!D19-'Weekly Entry'!D18>=0,"▲ ","▼ ")&TEXT(ABS('Weekly Entry'!D19-'Weekly Entry'!D18),"0.0%")&" vs. last week","") -> ▲ 5.5% vs. last week | H13: =IF(ISNUMBER('Weekly Entry'!G18),IF('Weekly Entry'!G19-'Weekly Entry'!G18>=0,"▲ ","▼ ")&TEXT(ABS('Weekly Entry'!G19-'Weekly Entry'!G18),"0.0%")&" vs. last week","") -> ▲ 1.3% vs. last week
B14: Trending up week-over-week | E14: Healthy: 50%+ | H14: Healthy: 90%+
B18: REVENUE COLLECTED | E18: CASELOAD HEALTH | H18: NOTES COMPLETION
B19: ='Weekly Entry'!H19 -> 17640 | E19: ='Weekly Entry'!K19 -> 1 | H19: ='Weekly Entry'!N19 -> 0.94339623
B20: =IF(ISNUMBER('Weekly Entry'!H18),IF('Weekly Entry'!H19-'Weekly Entry'!H18>=0,"▲ ","▼ ")&TEXT(ABS('Weekly Entry'!H19-'Weekly Entry'!H18),"$#,##0")&" vs. last week","") -> ▲ $240 vs. last week | E20: =IF(ISNUMBER('Weekly Entry'!K18),IF('Weekly Entry'!K19-'Weekly Entry'!K18>=0,"▲ ","▼ ")&TEXT(ABS('Weekly Entry'!K19-'Weekly Entry'!K18),"0.0%")&" vs. last week","") -> ▲ 0.0% vs. last week | H20: =IF(ISNUMBER('Weekly Entry'!N18),IF('Weekly Entry'!N19-'Weekly Entry'!N18>=0,"▲ ","▼ ")&TEXT(ABS('Weekly Entry'!N19-'Weekly Entry'!N18),"0.0%")&" vs. last week","") -> ▲ 3.8% vs. last week
B21: Cash, not billed | E21: Healthy: 80%+ at full | H21: Healthy: 90%+
B25: 12-Week Trend
B59: Update inputs on the Weekly Entry tab. Everything here recalculates automatically.

Sheet Weekly Entry
A1: Weekly Entry
A2: Log once a week — about 15 minutes. Blue cells are inputs. Black cells calculate themselves.
A6: Week | B6: Inquiries → Intakes | E6: Booked Hours vs. Goal | H6: Revenue | I6: Caseload Health | L6: Notes Completion
A7: Week ending | B7: Inquiries | C7: Intakes | D7: Conversion % | E7: Booked hours | F7: Goal hours | G7: % of goal | H7: Revenue collected | I7: Clinicians at/near full | J7: Clinicians under | K7: % healthy | L7: Notes on time | M7: Total notes due | N7: Completion %
A8: 46052 | B8: 8 | C8: 4 | D8: =IFERROR(C8/B8,0) -> 0.5 | E8: 118 | F8: 150 | G8: =IFERROR(E8/F8,0) -> 0.78666667 | H8: 14160 | I8: 3 | J8: 3 | K8: =IFERROR(I8/(I8+J8),0) -> 0.5 | L8: 28 | M8: 42 | N8: =IFERROR(L8/M8,0) -> 0.66666667
A9: 46059 | B9: 10 | C9: 6 | D9: =IFERROR(C9/B9,0) -> 0.6 | E9: 124 | F9: 150 | G9: =IFERROR(E9/F9,0) -> 0.82666667 | H9: 14880 | I9: 4 | J9: 2 | K9: =IFERROR(I9/(I9+J9),0) -> 0.66666667 | L9: 32 | M9: 45 | N9: =IFERROR(L9/M9,0) -> 0.71111111
A10: 46066 | B10: 12 | C10: 7 | D10: =IFERROR(C10/B10,0) -> 0.58333333 | E10: 132 | F10: 150 | G10: =IFERROR(E10/F10,0) -> 0.88 | H10: 15840 | I10: 4 | J10: 2 | K10: =IFERROR(I10/(I10+J10),0) -> 0.66666667 | L10: 35 | M10: 48 | N10: =IFERROR(L10/M10,0) -> 0.72916667
A11: 46073 | B11: 9 | C11: 5 | D11: =IFERROR(C11/B11,0) -> 0.55555556 | E11: 128 | F11: 150 | G11: =IFERROR(E11/F11,0) -> 0.85333333 | H11: 15360 | I11: 4 | J11: 2 | K11: =IFERROR(I11/(I11+J11),0) -> 0.66666667 | L11: 30 | M11: 46 | N11: =IFERROR(L11/M11,0) -> 0.65217391
A12: 46080 | B12: 14 | C12: 9 | D12: =IFERROR(C12/B12,0) -> 0.64285714 | E12: 138 | F12: 150 | G12: =IFERROR(E12/F12,0) -> 0.92 | H12: 16560 | I12: 5 | J12: 1 | K12: =IFERROR(I12/(I12+J12),0) -> 0.83333333 | L12: 40 | M12: 50 | N12: =IFERROR(L12/M12,0) -> 0.8
A13: 46087 | B13: 11 | C13: 8 | D13: =IFERROR(C13/B13,0) -> 0.72727273 | E13: 135 | F13: 150 | G13: =IFERROR(E13/F13,0) -> 0.9 | H13: 16200 | I13: 5 | J13: 1 | K13: =IFERROR(I13/(I13+J13),0) -> 0.83333333 | L13: 38 | M13: 49 | N13: =IFERROR(L13/M13,0) -> 0.7755102
A14: 46094 | B14: 13 | C14: 9 | D14: =IFERROR(C14/B14,0) -> 0.69230769 | E14: 140 | F14: 150 | G14: =IFERROR(E14/F14,0) -> 0.93333333 | H14: 16800 | I14: 5 | J14: 1 | K14: =IFERROR(I14/(I14+J14),0) -> 0.83333333 | L14: 42 | M14: 51 | N14: =IFERROR(L14/M14,0) -> 0.82352941
A15: 46101 | B15: 15 | C15: 11 | D15: =IFERROR(C15/B15,0) -> 0.73333333 | E15: 144 | F15: 150 | G15: =IFERROR(E15/F15,0) -> 0.96 | H15: 17280 | I15: 5 | J15: 1 | K15: =IFERROR(I15/(I15+J15),0) -> 0.83333333 | L15: 45 | M15: 52 | N15: =IFERROR(L15/M15,0) -> 0.86538462
A16: 46108 | B16: 12 | C16: 9 | D16: =IFERROR(C16/B16,0) -> 0.75 | E16: 142 | F16: 150 | G16: =IFERROR(E16/F16,0) -> 0.94666667 | H16: 17040 | I16: 5 | J16: 1 | K16: =IFERROR(I16/(I16+J16),0) -> 0.83333333 | L16: 46 | M16: 52 | N16: =IFERROR(L16/M16,0) -> 0.88461538
A17: 46115 | B17: 10 | C17: 7 | D17: =IFERROR(C17/B17,0) -> 0.7 | E17: 138 | F17: 150 | G17: =IFERROR(E17/F17,0) -> 0.92 | H17: 16560 | I17: 5 | J17: 1 | K17: =IFERROR(I17/(I17+J17),0) -> 0.83333333 | L17: 44 | M17: 50 | N17: =IFERROR(L17/M17,0) -> 0.88
A18: 46122 | B18: 14 | C18: 10 | D18: =IFERROR(C18/B18,0) -> 0.71428571 | E18: 145 | F18: 150 | G18: =IFERROR(E18/F18,0) -> 0.96666667 | H18: 17400 | I18: 6 | J18: 0 | K18: =IFERROR(I18/(I18+J18),0) -> 1 | L18: 48 | M18: 53 | N18: =IFERROR(L18/M18,0) -> 0.90566038
A19: 46129 | B19: 13 | C19: 10 | D19: =IFERROR(C19/B19,0) -> 0.76923077 | E19: 147 | F19: 150 | G19: =IFERROR(E19/F19,0) -> 0.98 | H19: 17640 | I19: 6 | J19: 0 | K19: =IFERROR(I19/(I19+J19),0) -> 1 | L19: 50 | M19: 53 | N19: =IFERROR(L19/M19,0) -> 0.94339623
D20: =IFERROR(C20/B20,0) -> 0 | G20: =IFERROR(E20/F20,0) -> 0 | K20: =IFERROR(I20/(I20+J20),0) -> 0 | N20: =IFERROR(L20/M20,0) -> 0
D21: =IFERROR(C21/B21,0) -> 0 | G21: =IFERROR(E21/F21,0) -> 0 | K21: =IFERROR(I21/(I21+J21),0) -> 0 | N21: =IFERROR(L21/M21,0) -> 0
D22: =IFERROR(C22/B22,0) -> 0 | G22: =IFERROR(E22/F22,0) -> 0 | K22: =IFERROR(I22/(I22+J22),0) -> 0 | N22: =IFERROR(L22/M22,0) -> 0
D23: =IFERROR(C23/B23,0) -> 0 | G23: =IFERROR(E23/F23,0) -> 0 | K23: =IFERROR(I23/(I23+J23),0) -> 0 | N23: =IFERROR(L23/M23,0) -> 0
D24: =IFERROR(C24/B24,0) -> 0 | G24: =IFERROR(E24/F24,0) -> 0 | K24: =IFERROR(I24/(I24+J24),0) -> 0 | N24: =IFERROR(L24/M24,0) -> 0
D25: =IFERROR(C25/B25,0) -> 0 | G25: =IFERROR(E25/F25,0) -> 0 | K25: =IFERROR(I25/(I25+J25),0) -> 0 | N25: =IFERROR(L25/M25,0) -> 0
D26: =IFERROR(C26/B26,0) -> 0 | G26: =IFERROR(E26/F26,0) -> 0 | K26: =IFERROR(I26/(I26+J26),0) -> 0 | N26: =IFERROR(L26/M26,0) -> 0
D27: =IFERROR(C27/B27,0) -> 0 | G27: =IFERROR(E27/F27,0) -> 0 | K27: =IFERROR(I27/(I27+J27),0) -> 0 | N27: =IFERROR(L27/M27,0) -> 0
D28: =IFERROR(C28/B28,0) -> 0 | G28: =IFERROR(E28/F28,0) -> 0 | K28: =IFERROR(I28/(I28+J28),0) -> 0 | N28: =IFERROR(L28/M28,0) -> 0
D29: =IFERROR(C29/B29,0) -> 0 | G29: =IFERROR(E29/F29,0) -> 0 | K29: =IFERROR(I29/(I29+J29),0) -> 0 | N29: =IFERROR(L29/M29,0) -> 0
D30: =IFERROR(C30/B30,0) -> 0 | G30: =IFERROR(E30/F30,0) -> 0 | K30: =IFERROR(I30/(I30+J30),0) -> 0 | N30: =IFERROR(L30/M30,0) -> 0
D31: =IFERROR(C31/B31,0) -> 0 | G31: =IFERROR(E31/F31,0) -> 0 | K31: =IFERROR(I31/(I31+J31),0) -> 0 | N31: =IFERROR(L31/M31,0) -> 0
... D33: =IFERROR(C33/B33,0) -> 0 | G33: =IFERROR(E33/F33,0) -> 0 | K33: =IFERROR(I33/(I33+J33),0) -> 0 | N33: =IFERROR(L33/M33,0) -> 0
A35: 12-week average | B35: =AVERAGE(B8:B19) -> 11.75 | C35: =AVERAGE(C8:C19) -> 7.9166667 | D35: =IFERROR(AVERAGE(C8:C19)/AVERAGE(B8:B19),0) -> 0.67375887 | E35: =AVERAGE(E8:E19) -> 135.91667 | F35: =AVERAGE(F8:F19) -> 150 | G35: =IFERROR(AVERAGE(E8:E19)/AVERAGE(F8:F19),0) -> 0.90611111 | H35: =AVERAGE(H8:H19) -> 16310 | I35: =AVERAGE(I8:I19) -> 4.75 | J35: =AVERAGE(J8:J19) -> 1.25 | K35: =IFERROR(AVERAGE(I8:I19)/(AVERAGE(I8:I19)+AVERAGE(J8:J19)),0) -> 0.79166667 | L35: =AVERAGE(L8:L19) -> 39.833333 | M35: =AVERAGE(M8:M19) -> 49.25 | N35: =IFERROR(AVERAGE(L8:L19)/AVERAGE(M8:M19),0) -> 0.80879865

Sheet 12-Week Trend
A1: 12-Week Trend
A2: Visual snapshot of where each KPI is trending. Update Weekly Entry; charts refresh automatically.
A4: Week | B4: Inquiries | C4: Conversion % | D4: % of booked-hours goal | E4: Revenue | F4: % clinicians healthy | G4: Notes completion %
A5: ='Weekly Entry'!A8 -> 46052 | B5: ='Weekly Entry'!B8 -> 8 | C5: ='Weekly Entry'!D8 -> 0.5 | D5: ='Weekly Entry'!G8 -> 0.78666667 | E5: ='Weekly Entry'!H8 -> 14160 | F5: ='Weekly Entry'!K8 -> 0.5 | G5: ='Weekly Entry'!N8 -> 0.66666667
A6: ='Weekly Entry'!A9 -> 46059 | B6: ='Weekly Entry'!B9 -> 10 | C6: ='Weekly Entry'!D9 -> 0.6 | D6: ='Weekly Entry'!G9 -> 0.82666667 | E6: ='Weekly Entry'!H9 -> 14880 | F6: ='Weekly Entry'!K9 -> 0.66666667 | G6: ='Weekly Entry'!N9 -> 0.71111111
A7: ='Weekly Entry'!A10 -> 46066 | B7: ='Weekly Entry'!B10 -> 12 | C7: ='Weekly Entry'!D10 -> 0.58333333 | D7: ='Weekly Entry'!G10 -> 0.88 | E7: ='Weekly Entry'!H10 -> 15840 | F7: ='Weekly Entry'!K10 -> 0.66666667 | G7: ='Weekly Entry'!N10 -> 0.72916667
A8: ='Weekly Entry'!A11 -> 46073 | B8: ='Weekly Entry'!B11 -> 9 | C8: ='Weekly Entry'!D11 -> 0.55555556 | D8: ='Weekly Entry'!G11 -> 0.85333333 | E8: ='Weekly Entry'!H11 -> 15360 | F8: ='Weekly Entry'!K11 -> 0.66666667 | G8: ='Weekly Entry'!N11 -> 0.65217391
A9: ='Weekly Entry'!A12 -> 46080 | B9: ='Weekly Entry'!B12 -> 14 | C9: ='Weekly Entry'!D12 -> 0.64285714 | D9: ='Weekly Entry'!G12 -> 0.92 | E9: ='Weekly Entry'!H12 -> 16560 | F9: ='Weekly Entry'!K12 -> 0.83333333 | G9: ='Weekly Entry'!N12 -> 0.8
A10: ='Weekly Entry'!A13 -> 46087 | B10: ='Weekly Entry'!B13 -> 11 | C10: ='Weekly Entry'!D13 -> 0.72727273 | D10: ='Weekly Entry'!G13 -> 0.9 | E10: ='Weekly Entry'!H13 -> 16200 | F10: ='Weekly Entry'!K13 -> 0.83333333 | G10: ='Weekly Entry'!N13 -> 0.7755102
A11: ='Weekly Entry'!A14 -> 46094 | B11: ='Weekly Entry'!B14 -> 13 | C11: ='Weekly Entry'!D14 -> 0.69230769 | D11: ='Weekly Entry'!G14 -> 0.93333333 | E11: ='Weekly Entry'!H14 -> 16800 | F11: ='Weekly Entry'!K14 -> 0.83333333 | G11: ='Weekly Entry'!N14 -> 0.82352941
A12: ='Weekly Entry'!A15 -> 46101 | B12: ='Weekly Entry'!B15 -> 15 | C12: ='Weekly Entry'!D15 -> 0.73333333 | D12: ='Weekly Entry'!G15 -> 0.96 | E12: ='Weekly Entry'!H15 -> 17280 | F12: ='Weekly Entry'!K15 -> 0.83333333 | G12: ='Weekly Entry'!N15 -> 0.86538462
A13: ='Weekly Entry'!A16 -> 46108 | B13: ='Weekly Entry'!B16 -> 12 | C13: ='Weekly Entry'!D16 -> 0.75 | D13: ='Weekly Entry'!G16 -> 0.94666667 | E13: ='Weekly Entry'!H16 -> 17040 | F13: ='Weekly Entry'!K16 -> 0.83333333 | G13: ='Weekly Entry'!N16 -> 0.88461538
A14: ='Weekly Entry'!A17 -> 46115 | B14: ='Weekly Entry'!B17 -> 10 | C14: ='Weekly Entry'!D17 -> 0.7 | D14: ='Weekly Entry'!G17 -> 0.92 | E14: ='Weekly Entry'!H17 -> 16560 | F14: ='Weekly Entry'!K17 -> 0.83333333 | G14: ='Weekly Entry'!N17 -> 0.88
A15: ='Weekly Entry'!A18 -> 46122 | B15: ='Weekly Entry'!B18 -> 14 | C15: ='Weekly Entry'!D18 -> 0.71428571 | D15: ='Weekly Entry'!G18 -> 0.96666667 | E15: ='Weekly Entry'!H18 -> 17400 | F15: ='Weekly Entry'!K18 -> 1 | G15: ='Weekly Entry'!N18 -> 0.90566038
A16: ='Weekly Entry'!A19 -> 46129 | B16: ='Weekly Entry'!B19 -> 13 | C16: ='Weekly Entry'!D19 -> 0.76923077 | D16: ='Weekly Entry'!G19 -> 0.98 | E16: ='Weekly Entry'!H19 -> 17640 | F16: ='Weekly Entry'!K19 -> 1 | G16: ='Weekly Entry'!N19 -> 0.94339623

Sheet How to Use
B1: How to Use This Sheet
B2: The weekly dashboard every group practice owner needs.
B5: The idea
B6: Most group practice owners either track nothing — or track so much they stop looking. This dashboard is the middle path: six numbers, logged once a week, that tell you whether your practice is actually healthy.
B8: Set aside 15 minutes at the end of each week. Pull your numbers from your EHR, your bookkeeping, and your team. Fill in the BLUE cells on the Weekly Entry tab. The BLACK cells (percentages, averages, trends) calculate themselves.
B10: After four weeks you'll start seeing patterns. After twelve, you'll have something powerful: data you trust, for decisions you've been putting off.
B12: The six KPIs
B15: 1. New client inquiries
B16: What it is | C16: Every first-touch contact from a prospective client — phone, form, email, referral, whatever.
B17: Why it matters | C17: This is your top-of-funnel reality check. A dip here shows up weeks later as a caseload problem. Spot it early.
B18: Benchmarks | C18: Green: trending flat or up week-over-week. · Yellow: two weeks of decline. · Red: three+ weeks of decline — time to look at marketing, referral partners, and SEO.
B20: 2. Inquiry → intake conversion %
B21: What it is | C21: Intakes this week ÷ inquiries this week. Some of this week's intakes came from last week's inquiries — that's fine. You're tracking the ratio over time, not matching individual people.
B22: Why it matters | C22: Inquiries don't pay rent. Intakes do. A low conversion rate means something is leaking in your response process — speed, pricing, fit, or follow-up.
B23: Benchmarks | C23: Green: 50%+ · Yellow: 35–50% · Red: under 35% — look at response time, admin process, and how your clinicians convert the consult call.
B25: 3. Booked hours vs. productivity goal
B26: What it is | C26: Total booked clinical hours across the team ÷ your weekly productivity goal (e.g., 6 clinicians × 25 hours = 150).
B27: Why it matters | C27: This is the number that connects caseload to revenue. Booked hours lag when you're underscheduling, not filling cancellations, or carrying clinicians who aren't ramping.
B28: Benchmarks | C28: Green: 90%+ · Yellow: 75–90% · Red: under 75% — something structural is off (intake flow, caseload distribution, or clinician capacity).
B30: 4. Weekly revenue collected
B31: What it is | C31: Cash actually collected this week — not billed, not invoiced. Collected.
B32: Why it matters | C32: Billed revenue is optimism. Collected revenue is reality. Watching this weekly catches insurance lag, billing errors, and cash-flow surprises before they become crises.
B33: Benchmarks | C33: Set your own floor based on payroll + overhead. If weekly collections fall below that floor for two weeks in a row, pull up your A/R aging.
B35: 5. Clinician caseload health
B36: What it is | C36: % of clinicians at or near full caseload vs. under caseload. You define 'full' — it's usually 22–28 weekly client hours depending on your model.
B37: Why it matters | C37: Averages lie. One full clinician and one empty clinician averages to 'fine' — but you've got a burnout risk AND an underutilized hire. This metric keeps both visible.
B38: Benchmarks | C38: Green: 80%+ healthy · Yellow: 60–80% · Red: under 60% — you have a caseload distribution problem, not a volume problem.
B40: 6. Notes completion %
B41: What it is | C41: Notes completed on time this week ÷ total notes due this week. 'On time' = whatever your policy says (often within 24–48 hours).
B42: Why it matters | C42: Late notes are the canary in the coal mine for clinician overwhelm, documentation drag, and billing delays. It's also a compliance issue waiting to happen.
B43: Benchmarks | C43: Green: 90%+ · Yellow: 75–90% · Red: under 75% — have a conversation with your team this week, not next month.
B46: A closing note
B48: The goal isn't perfection — it's rhythm. Fifteen minutes, once a week, every week. The practice owners I've seen thrive aren't the ones with the fanciest dashboards. They're the ones who actually look at the numbers before the numbers become a problem.
B50: — Bailey
